ct_random_function/__init__.py
ct_random_function/calculator.py
ct_random_function-0.0.3.dist-info/METADATA
ct_random_function-0.0.3.dist-info/WHEEL
ct_random_function-0.0.3.dist-info/top_level.txt
ct_random_function-0.0.3.dist-info/RECORD
