Metadata-Version: 2.1
Name: ct_random_function
Version: 0.0.3
Summary: This is my very first package from me
Home-page: https://github.com/CuongTon
Author: Cuong Ton
Author-email: tonkiencuong@gmail.com
License: MIT
Requires-Python: >=3.8
Requires-Dist: pandas >=1.0.0
